getdeck/__init__.py
getdeck/__main__.py
getdeck/cli/__init__.py
getdeck/cli/console.py
getdeck/cli/get.py
getdeck/cli/hosts.py
getdeck/cli/list.py
getdeck/cli/remove.py
getdeck/cli/stop.py
getdeck/cli/telemetry.py
getdeck/cli/utils.py
getdeck/cli/version.py
getdeck/configuration.py
getdeck/deckfile/__init__.py
getdeck/deckfile/deckfile_1.py
getdeck/deckfile/errors.py
getdeck/deckfile/file.py
getdeck/deckfile/selector.py
getdeck/fetch/__init__.py
getdeck/fetch/deck_fetcher.py
getdeck/fetch/fetch.py
getdeck/fetch/source_fetcher.py
getdeck/fetch/types.py
getdeck/fetch/utils.py
getdeck/k8s.py
getdeck/provider/__init__.py
getdeck/provider/abstract.py
getdeck/provider/beiboot/__init__.py
getdeck/provider/errors.py
getdeck/provider/factory.py
getdeck/provider/k3d/__init__.py
getdeck/provider/kind/__init__.py
getdeck/provider/kubectl/__init__.py
getdeck/provider/types.py
getdeck/provider/utility_provider.py
getdeck/sources/__init__.py
getdeck/sources/file.py
getdeck/sources/generator.py
getdeck/sources/helm.py
getdeck/sources/inline.py
getdeck/sources/kustomize.py
getdeck/sources/selector.py
getdeck/sources/tooler.py
getdeck/sources/types.py
getdeck/sources/utils.py
getdeck/telemetry/__init__.py
getdeck/telemetry/telemetry.py
getdeck/utils.py
getdeck-0.11.1.dist-info/entry_points.txt
getdeck-0.11.1.dist-info/LICENSE
getdeck-0.11.1.dist-info/WHEEL
getdeck-0.11.1.dist-info/METADATA
getdeck-0.11.1.dist-info/RECORD
